odecast/__init__.py
odecast/analyze.py
odecast/api.py
odecast/compile.py
odecast/equation.py
odecast/errors.py
odecast/reduce.py
odecast/solution.py
odecast/symbols.py
odecast/validate.py
odecast/backends/__init__.py
odecast/backends/scipy_bvp.py
odecast/backends/scipy_ivp.py
odecast/backends/sympy_backend.py
odecast-0.1.1.dist-info/METADATA
odecast-0.1.1.dist-info/WHEEL
odecast-0.1.1.dist-info/licenses/LICENSE
odecast-0.1.1.dist-info/RECORD
