Metadata-Version: 2.4
Name: odecast
Version: 0.1.1
Summary: A Python library for solving higher-order ordinary differential equations (ODEs) without manual reduction.
Project-URL: Homepage, https://github.com/maroba/odecast
Project-URL: Repository, https://github.com/maroba/odecast
Author-email: Matthias Baer <matthias.r.baer@googlemail.com>
License-Expression: MIT
License-File: LICENSE
Classifier: Development Status :: 3 - Alpha
Classifier: Intended Audience :: Developers
Classifier: License :: OSI Approved :: MIT License
Classifier: Programming Language :: Python :: 3
Classifier: Programming Language :: Python :: 3.10
Classifier: Programming Language :: Python :: 3.11
Classifier: Programming Language :: Python :: 3.12
Requires-Python: >=3.10
Provides-Extra: dev
Requires-Dist: pytest; extra == 'dev'
Requires-Dist: pytest-cov; extra == 'dev'
Provides-Extra: math
Requires-Dist: matplotlib; extra == 'math'
Requires-Dist: numpy; extra == 'math'
Requires-Dist: scipy; extra == 'math'
Requires-Dist: sympy; extra == 'math'
